sentry_config/__init__.py
sentry_config/config.py
sentry_config/criteria.py
sentry_config/exceptions.py
sentry_config/validators.py
SentryConfig-1.0.1.dist-info/LICENSE.md
SentryConfig-1.0.1.dist-info/METADATA
SentryConfig-1.0.1.dist-info/WHEEL
SentryConfig-1.0.1.dist-info/top_level.txt
SentryConfig-1.0.1.dist-info/RECORD
